{"authors.": {"authors": ["Adam Gandelman", "Sean Dague", "Jakub Libosvar", "Armando Migliaccio", "Dean Troyer", "Ian Wienand", "Joe Gordon", "Mauro Rodrigues", "Clark Boylan", "Han Zhou", "Lance Bragstad", "Monty Taylor"], "commits": [7, 7, 3, 2, 2, 2, 2, 2, 1, 1, 1, 1], "id": [50, 49, 630, 477, 1132, 692, 36, 1112, 7, 824, 1417, 1]}, "authors.last month": {"authors": ["Adam Gandelman", "Dean Troyer"], "commits": [1, 1], "id": [50, 1132]}, "authors.last year": {"authors": ["Adam Gandelman", "Sean Dague", "Jakub Libosvar", "Armando Migliaccio", "Dean Troyer", "Ian Wienand", "Joe Gordon", "Mauro Rodrigues", "Clark Boylan", "Han Zhou", "Lance Bragstad", "Monty Taylor"], "commits": [7, 7, 3, 2, 2, 2, 2, 2, 1, 1, 1, 1], "id": [50, 49, 630, 477, 1132, 692, 36, 1112, 7, 824, 1417, 1]}}