{"authors.": {"authors": ["Christian Berendt", "Shilla Saebi", "Matt Kassawara", "Andreas Jaeger", "darrenchan", "Gauvain Pocentek", "Anne Gentle", "Ildiko", "KATO Tomoyuki", "Tom Fifield", "Erik Wilson", "Mate Lakat", "Laurel Michaels", "Alexandra Settle", "Joseph Robinson", "Alexander Adamov", "Lana Brindley", "Li Yingjun", "Maria Zlatkova", "OlgaGusarenko", "Thomas Goirand", "Anish Bhatt", "Gordon Chung", "Kylin CG", "Shawhin Tech", "Bob-OpenStack", "Kurt Martin", "Steve Martinelli", "Tamara Johnston", "Deepti Navale", "Dhriti Shikhar", "don", "Doug Hellmann", "Jeegn Chen", "Karin Levenstein", "Lena", "Olena Logvinova", "Robb Romans", "Scott Lowe", "Shay Halsband", "Stephen Gordon", "Tanja Roth", "zhangtralon", "Adelina Tuvenie", "Angus Salkeld", "Ben Silverman", "Bob Callaway", "Chris J Arges", "daisy-ycguo", "Jeffrey Olsen", "Joshua Harlow", "kallimachos", "Ken'ichi Ohmichi", "Konstantinos Papadopoulos", "Lena Novokshonova", "LingxianKong", "Pedro Navarro Perez", "Phil Hopkins", "Sam Yaple", "Sean McGinnis", "Steven Deaton", "Sungjin Kang", "Vic Howard", "Vipin Balachandran", "Yair Fried", "YAMAMOTO Takashi", "Adrian Smith", "Alexis GUNST", "alexpilotti", "Anthony Lee", "Arvind Somy", "asettle", "Ashish Billore", "Bernd Bausch", "Bertie Fulton", "Blake Smith", "Brad Lodgen", "Brent Roskos", "Britt Houser", "Chenhao", "chris", "Chris Blumentritt", "Chris Grivas", "Chris Ricker", "Christopher Aedo", "Dan Sneddon", "Daniel Wilson", "Davanum Srinivas", "Denis M", "Edgar Magana", "Elena Ezhova", "elkev", "Eoghan Glynn", "Hideaki Suzuki", "Hiroki Aramaki", "Itzik Brown", "Joe H. Rahme", "Jonathan Proulx", "Julien Danjou", "Jun Ishizaki"], "commits": [70, 48, 43, 40, 35, 27, 19, 19, 15, 15, 14, 14, 13, 11, 10, 9, 8, 8, 8, 7, 7, 5, 5, 5, 5, 4, 4, 4, 4, 3, 3, 3, 3, 3, 3, 3, 3, 3, 3, 3, 3, 3, 3, 2, 2, 2, 2, 2, 2, 2, 2, 2, 2, 2, 2, 2, 2, 2, 2, 2, 2, 2, 2, 2, 2, 2, 1, 1, 1, 1, 1, 1, 1, 1, 1, 1, 1, 1, 1, 1, 1, 1, 1, 1, 1, 1, 1, 1, 1, 1, 1, 1, 1, 1, 1, 1, 1, 1, 1, 1], "id": [361, 1545, 2372, 194, 3204, 306, 138, 1535, 1569, 94, 614821, 69, 2809, 3224, 3125, 615408, 3195, 162, 618396, 617921, 1454, 617919, 754, 1944, 616156, 615155, 86, 1154, 615770, 3177, 615581, 618783, 62, 374, 1579, 612399, 618097, 3057, 612447, 402, 729, 615948, 2761, 414, 954, 617826, 268, 619034, 72, 615949, 159, 3255, 121, 612407, 309900, 1241, 64, 2814, 614324, 577099, 981, 618395, 2019, 243, 1236, 556, 880, 3250, 76, 372, 440, 3248, 618044, 619501, 617436, 618745, 617279, 2311, 814, 617681, 1172, 615675, 612350, 3044, 617399, 3258, 613390, 80, 1711, 432, 195, 614943, 19, 615366, 618746, 656, 1228, 2144, 47, 409]}, "authors.last month": {"authors": ["Christian Berendt", "Andreas Jaeger", "Anne Gentle", "Ildiko", "KATO Tomoyuki", "Shilla Saebi", "darrenchan", "Gauvain Pocentek", "Alexander Adamov", "Alexandra Settle", "Anish Bhatt", "Gordon Chung", "Maria Zlatkova", "OlgaGusarenko", "don", "Lana Brindley", "Steve Martinelli", "Chris J Arges", "daisy-ycguo", "Deepti Navale", "Doug Hellmann", "Joseph Robinson", "Laurel Michaels", "Alexis GUNST", "Anthony Lee", "Arvind Somy", "asettle", "Bernd Bausch", "Blake Smith", "Bob-OpenStack", "Brent Roskos", "chris", "Dan Sneddon", "Daniel Wilson", "Elena Ezhova", "Erik Wilson", "Hiroki Aramaki", "Jonathan Proulx", "Jun Wang", "kallimachos", "Karen Bradshaw", "Karin Levenstein", "Kurt Martin", "LingxianKong", "Matt Kassawara", "Matt Ray", "Nicholas Chase", "Olena Logvinova", "Rich Hagarty", "Richard Hedlind", "Rico Lin", "Romain Hardouin", "Sean McGinnis", "Sungjin Kang", "Swann Croiset", "Takashi NATSUME", "Tim Swanson", "yanlin ren"], "commits": [31, 19, 13, 12, 9, 8, 6, 6, 5, 5, 5, 5, 5, 5, 3, 3, 3, 2, 2, 2, 2, 2, 2, 1, 1, 1, 1, 1, 1, 1, 1, 1, 1, 1, 1, 1, 1, 1, 1, 1, 1, 1, 1, 1, 1, 1, 1, 1, 1, 1, 1, 1, 1, 1, 1, 1, 1, 1], "id": [361, 194, 138, 1535, 1569, 1545, 3204, 306, 615408, 3224, 617919, 754, 618396, 617921, 618783, 3195, 1154, 619034, 72, 3177, 62, 3125, 2809, 3250, 372, 440, 3248, 619501, 618745, 615155, 2311, 1172, 3258, 613390, 195, 614821, 618746, 2144, 618784, 3255, 620077, 1579, 86, 1241, 2372, 876, 3170, 618097, 3329, 614294, 619545, 2621, 577099, 618395, 1488, 258, 619500, 620076]}, "authors.last year": {"authors": ["Christian Berendt", "Shilla Saebi", "Matt Kassawara", "Andreas Jaeger", "darrenchan", "Gauvain Pocentek", "Anne Gentle", "Ildiko", "KATO Tomoyuki", "Tom Fifield", "Erik Wilson", "Mate Lakat", "Laurel Michaels", "Alexandra Settle", "Joseph Robinson", "Alexander Adamov", "Lana Brindley", "Li Yingjun", "Maria Zlatkova", "OlgaGusarenko", "Thomas Goirand", "Anish Bhatt", "Gordon Chung", "Kylin CG", "Shawhin Tech", "Bob-OpenStack", "Kurt Martin", "Steve Martinelli", "Tamara Johnston", "Deepti Navale", "Dhriti Shikhar", "don", "Doug Hellmann", "Jeegn Chen", "Karin Levenstein", "Lena", "Olena Logvinova", "Robb Romans", "Scott Lowe", "Shay Halsband", "Stephen Gordon", "Tanja Roth", "zhangtralon", "Adelina Tuvenie", "Angus Salkeld", "Ben Silverman", "Bob Callaway", "Chris J Arges", "daisy-ycguo", "Jeffrey Olsen", "Joshua Harlow", "kallimachos", "Ken'ichi Ohmichi", "Konstantinos Papadopoulos", "Lena Novokshonova", "LingxianKong", "Pedro Navarro Perez", "Phil Hopkins", "Sam Yaple", "Sean McGinnis", "Steven Deaton", "Sungjin Kang", "Vic Howard", "Vipin Balachandran", "Yair Fried", "YAMAMOTO Takashi", "Adrian Smith", "Alexis GUNST", "alexpilotti", "Anthony Lee", "Arvind Somy", "asettle", "Ashish Billore", "Bernd Bausch", "Bertie Fulton", "Blake Smith", "Brad Lodgen", "Brent Roskos", "Britt Houser", "Chenhao", "chris", "Chris Blumentritt", "Chris Grivas", "Chris Ricker", "Christopher Aedo", "Dan Sneddon", "Daniel Wilson", "Davanum Srinivas", "Denis M", "Edgar Magana", "Elena Ezhova", "elkev", "Eoghan Glynn", "Hideaki Suzuki", "Hiroki Aramaki", "Itzik Brown", "Joe H. Rahme", "Jonathan Proulx", "Julien Danjou", "Jun Ishizaki"], "commits": [70, 48, 43, 40, 35, 27, 19, 19, 15, 15, 14, 14, 13, 11, 10, 9, 8, 8, 8, 7, 7, 5, 5, 5, 5, 4, 4, 4, 4, 3, 3, 3, 3, 3, 3, 3, 3, 3, 3, 3, 3, 3, 3, 2, 2, 2, 2, 2, 2, 2, 2, 2, 2, 2, 2, 2, 2, 2, 2, 2, 2, 2, 2, 2, 2, 2, 1, 1, 1, 1, 1, 1, 1, 1, 1, 1, 1, 1, 1, 1, 1, 1, 1, 1, 1, 1, 1, 1, 1, 1, 1, 1, 1, 1, 1, 1, 1, 1, 1, 1], "id": [361, 1545, 2372, 194, 3204, 306, 138, 1535, 1569, 94, 614821, 69, 2809, 3224, 3125, 615408, 3195, 162, 618396, 617921, 1454, 617919, 754, 1944, 616156, 615155, 86, 1154, 615770, 3177, 615581, 618783, 62, 374, 1579, 612399, 618097, 3057, 612447, 402, 729, 615948, 2761, 414, 954, 617826, 268, 619034, 72, 615949, 159, 3255, 121, 612407, 309900, 1241, 64, 2814, 614324, 577099, 981, 618395, 2019, 243, 1236, 556, 880, 3250, 76, 372, 440, 3248, 618044, 619501, 617436, 618745, 617279, 2311, 814, 617681, 1172, 615675, 612350, 3044, 617399, 3258, 613390, 80, 1711, 432, 195, 614943, 19, 615366, 618746, 656, 1228, 2144, 47, 409]}}