{"authors": ["Andreas Jaeger", "Christian Berendt", "Roger Luethi", "Gauvain Pocentek", "Shilla Saebi", "Diane Fleming", "Anne Gentle", "Pranav Salunke", "KATO Tomoyuki", "Matt Kassawara"], "commits": [473, 245, 223, 117, 85, 84, 80, 76, 56, 54], "companies": ["SUSE", "Rackspace", "B1 Systems", "Objectif-libre", "Comcast", "Red Hat", "Aptira", "Fujitsu", "HP", "Huawei"], "company_commits": [473, 251, 250, 119, 89, 78, 76, 58, 55, 39], "id": [194, 361, 1558, 306, 1545, 1362, 138, 1319, 1569, 2372]}