{"senders.": {"id": [853, 1614, 581235, 3274, 2591, 582859, 891, 581540, 94, 580576], "senders": ["Stefano Maffulli", "alop", "alex-tuxx", "George Shuklin", "Joe Topjian", "jjpavlik@gmail.com", "Robert van Leeuwen", "jeffsilverm", "Tom Fifield", "alawson"], "sent": [72, 56, 34, 34, 30, 28, 28, 25, 23, 22]}, "senders.last month": {"id": [1102, 1614, 582859, 2591, 853, 1983, 3274, 108, 891, 581235], "senders": ["Slawomir Kaplonski", "alop", "jjpavlik@gmail.com", "Joe Topjian", "Stefano Maffulli", "Belmiro Moreira", "George Shuklin", "Mathieu Gagne\u0301", "Robert van Leeuwen", "alex-tuxx"], "sent": [15, 12, 9, 9, 9, 7, 7, 7, 7, 6]}, "senders.last year": {"id": [853, 1614, 581235, 3274, 2591, 582859, 891, 581540, 94, 580576], "senders": ["Stefano Maffulli", "alop", "alex-tuxx", "George Shuklin", "Joe Topjian", "jjpavlik@gmail.com", "Robert van Leeuwen", "jeffsilverm", "Tom Fifield", "alawson"], "sent": [72, 56, 34, 34, 30, 28, 28, 25, 23, 22]}}