{"diff_netsenders_30": -295, "diff_netsenders_365": 3739, "diff_netsenders_7": 49, "diff_netsent_30": -3025, "diff_netsent_365": 1383385, "diff_netsent_7": 2047, "first_date": "2014-04-17", "last_date": "2014-10-15", "percentage_senders_30": 14, "percentage_senders_365": 73, "percentage_senders_7": 6, "percentage_sent_30": 1, "percentage_sent_365": 235, "percentage_sent_7": 5, "repositories": 25, "senders": 5819, "senders_30": 1800, "senders_365": 8833, "senders_7": 829, "sent": 1040287, "sent_30": 166324, "sent_365": 1971106, "sent_7": 38480}