{"authors.": {"authors": ["Derek Higgins", "Dan Prince", "Gregory Haynes", "rbtcollins", "Alexis Lee", "Ben Nemec", "Richard Su", "Steve Kowalik", "Ghe Rivero", "James Polley"], "commits": [51, 12, 6, 6, 2, 2, 2, 2, 1, 1], "id": [618, 26, 1390, 516, 818, 193, 1378, 830, 13, 1366]}, "authors.last month": {"authors": ["Derek Higgins", "Gregory Haynes", "Dan Prince", "Lucas Alvares Gomes", "rbtcollins"], "commits": [8, 3, 2, 1, 1], "id": [618, 1390, 26, 85, 516]}, "authors.last year": {"authors": ["Derek Higgins", "Dan Prince", "Gregory Haynes", "rbtcollins", "Alexis Lee", "Ben Nemec", "Richard Su", "Steve Kowalik", "Ghe Rivero", "James Polley"], "commits": [51, 12, 6, 6, 2, 2, 2, 2, 1, 1], "id": [618, 26, 1390, 516, 818, 193, 1378, 830, 13, 1366]}}