{"panels": {"panel1": {"widgets": [{"from": "Jan 1970", "to": "Apr 2015", "title": "Example Time Widget", "color": "rgb(170, 170, 170)", "series": [{"nameUser": "added lines", "name": "added_lines", "form": "spline"}, {"nameUser": "removed lines", "name": "removed_lines", "form": "spline"}], "typeData": "scm", "jsons": "templates/json/scm-evolutionary.json", "y": 11, "x": 5, "size": 544, "type": "HighTime", "id": 1, "readingData": "scm"}, {"title": "Example Info Widget", "color": "rgb(170, 170, 170)", "series": [{"nameUser": "added lines ", "type": "column", "name": "added_lines"}, {"nameUser": "removed lines ", "type": "column", "name": "removed_lines"}], "typeData": "scm", "jsons": "templates/json/scm-static.json", "y": 1, "x": 5, "type": "HighInfo", "id": 2, "readingData": "scm"}, {"width": 10, "url": "https://youtu.be/nKjXwXUIbRk", "height": 10, "content": "<iframe src=\"http://www.youtube.com/embed/nKjXwXUIbRk\" width=\"270\" height=\"230\" frameborder=\"0\" allowfullscreen></iframe>", "color": "rgb(170, 170, 170)", "y": 1, "x": 21, "type": "VideoWidget", "id": 3}], "panel": {"color": "#aaaaaa", "reading": {"scm": "scm", "mls": "mls", "irc": "irc", "its": "its", "scr": "scr"}, "id": 1, "name": "Example Panel"}}}, "name": "Make Graphics"}