{"closers.": {"closed": [176, 137, 104, 78, 64, 55, 52, 49, 42, 41, 39, 36, 34, 28, 27, 26, 25, 25, 22, 21, 21, 21, 20, 19, 19, 18, 16, 16, 15, 15, 14, 14, 14, 14, 12, 12, 11, 11, 10, 9, 9, 9, 8, 8, 7, 7, 7, 6, 6, 6, 6, 6, 5, 5, 5, 5, 3, 3, 3, 3, 3, 3, 3, 3, 2, 2, 2, 2, 2, 2, 2, 2, 2, 2, 2, 2, 2, 2, 2, 2, 1, 1, 1, 1, 1, 1, 1, 1, 1, 1, 1, 1, 1], "closers": ["Dmitry Borodaenko", "Vladimir Kuklin", "Bogdan Dobrelya", "Sergey Lukjanov", "Dmitry Pyzhov", "Mike Scherbakov", "Matthew Mosesohn", "dburmistrov", "Serg Melikyan", "tatyana.leontovich@gmail.com", "efedorova", "Roman Podolyaka", "Timur Sufiev", "enikanorov", "Valeriy Ponomaryov", "idv1985", "alekseyk.ru@gmail.com", "vkramskikh@gmail.com", "igor@kalnitsky.org", "Aleksandra Fedorova", "holser@gmail.com", "jkirnosova", "mrasskazov", "dmitryme", "Ilya Sviridov", "vsharshov@mirantis.com", "Dina Belova", "Ruslan Kamaldinov", "Evgeniy L", "xenolog", "Dmitry Shulyak", "e0ne", "ishishkin", "vparakhin", "gcon.monolake@gmail.com", "Oleg Bondarev", "Alexander Ignatov", "Victor Sergeyev", "Angus Salkeld", "Illia Khudoshyn", "Konovalov-Nik", "sbogatkin", "iyozhikov", "nmarkov", "Boris Pavlovic", "Denis Egorenko", "Sergey Galkin", "Denis M", "diakunchikov", "ipovolotskaya", "prmtl", "xdeller", "Pekelny Ilya", "Sergey Kolekonov", "Sergey Reshetnyak", "Yuriy Taraday", "Andrew Lazarev", "dtyzhnenko", "Ilya Shakhat", "nerminamiller", "pkaminski", "Ryan Moe", "Stan Lagun", "Vladimir Kozhukalov", "akislitsky", "Alexei Kornienko", "Andrew Woodward", "Andrey Epifanov", "Andrey Kurilin", "Andrey Pavlov", "Ann Kamyshnikova", "Dmitriy Ukhlov", "Elena Ezhova", "jaypipes", "Piotr Siwczak", "Sergey Nikitin", "srogov", "Vadim Rovachev", "Yuriy Zveryanskyy", "yyekovenko", "Alexander Kuznetsov", "DreidelLhasa@yahoo.com", "dsokolov@mirantis.com", "ekozhemyakin", "eshumakher", "fsoppelsa", "Pavlo Shchelokovskyy", "Roman Prykhodchenko", "Sergey Kraynev", "vitalij-ua", "Vitaly Gridnev", "Vladyslav Drok", "Yaroslav Lobankov"], "id": [271, 2250, 1426, 731, 1639, 1837, 1637, 579937, 1613, 578473, 1635, 140, 1070, 505, 1266, 579717, 579690, 579711, 580278, 1681, 580709, 578030, 580104, 1012, 1664, 579741, 1029, 993, 3114, 579688, 283, 242, 579691, 580548, 579689, 509, 772, 363, 954, 2784, 992, 581209, 579888, 579744, 398, 1044, 1732, 1711, 579321, 581884, 581395, 579670, 643, 774, 1021, 83, 1030, 581764, 514, 3049, 582047, 746, 2242, 1641, 580598, 383, 2160, 809, 1002, 1047, 141, 2785, 195, 654, 462, 1284, 581353, 1014, 153, 579886, 1019, 580369, 580357, 580633, 580759, 581729, 1493, 521, 1109, 579328, 1049, 2551, 1018]}, "closers.last month": {"closed": [176, 137, 104, 78, 64, 55, 52, 49, 42, 41, 39, 36, 34, 28, 27, 26, 25, 25, 22, 21, 21, 21, 20, 19, 19, 18, 16, 16, 15, 15, 14, 14, 14, 14, 12, 12, 11, 11, 10, 9, 9, 9, 8, 8, 7, 7, 7, 6, 6, 6, 6, 6, 5, 5, 5, 5, 3, 3, 3, 3, 3, 3, 3, 3, 2, 2, 2, 2, 2, 2, 2, 2, 2, 2, 2, 2, 2, 2, 2, 2, 1, 1, 1, 1, 1, 1, 1, 1, 1, 1, 1, 1, 1], "closers": ["Dmitry Borodaenko", "Vladimir Kuklin", "Bogdan Dobrelya", "Sergey Lukjanov", "Dmitry Pyzhov", "Mike Scherbakov", "Matthew Mosesohn", "dburmistrov", "Serg Melikyan", "tatyana.leontovich@gmail.com", "efedorova", "Roman Podolyaka", "Timur Sufiev", "enikanorov", "Valeriy Ponomaryov", "idv1985", "alekseyk.ru@gmail.com", "vkramskikh@gmail.com", "igor@kalnitsky.org", "Aleksandra Fedorova", "holser@gmail.com", "jkirnosova", "mrasskazov", "dmitryme", "Ilya Sviridov", "vsharshov@mirantis.com", "Dina Belova", "Ruslan Kamaldinov", "Evgeniy L", "xenolog", "Dmitry Shulyak", "e0ne", "ishishkin", "vparakhin", "gcon.monolake@gmail.com", "Oleg Bondarev", "Alexander Ignatov", "Victor Sergeyev", "Angus Salkeld", "Illia Khudoshyn", "Konovalov-Nik", "sbogatkin", "iyozhikov", "nmarkov", "Boris Pavlovic", "Denis Egorenko", "Sergey Galkin", "Denis M", "diakunchikov", "ipovolotskaya", "prmtl", "xdeller", "Pekelny Ilya", "Sergey Kolekonov", "Sergey Reshetnyak", "Yuriy Taraday", "Andrew Lazarev", "dtyzhnenko", "Ilya Shakhat", "nerminamiller", "pkaminski", "Ryan Moe", "Stan Lagun", "Vladimir Kozhukalov", "akislitsky", "Alexei Kornienko", "Andrew Woodward", "Andrey Epifanov", "Andrey Kurilin", "Andrey Pavlov", "Ann Kamyshnikova", "Dmitriy Ukhlov", "Elena Ezhova", "jaypipes", "Piotr Siwczak", "Sergey Nikitin", "srogov", "Vadim Rovachev", "Yuriy Zveryanskyy", "yyekovenko", "Alexander Kuznetsov", "DreidelLhasa@yahoo.com", "dsokolov@mirantis.com", "ekozhemyakin", "eshumakher", "fsoppelsa", "Pavlo Shchelokovskyy", "Roman Prykhodchenko", "Sergey Kraynev", "vitalij-ua", "Vitaly Gridnev", "Vladyslav Drok", "Yaroslav Lobankov"], "id": [271, 2250, 1426, 731, 1639, 1837, 1637, 579937, 1613, 578473, 1635, 140, 1070, 505, 1266, 579717, 579690, 579711, 580278, 1681, 580709, 578030, 580104, 1012, 1664, 579741, 1029, 993, 3114, 579688, 283, 242, 579691, 580548, 579689, 509, 772, 363, 954, 2784, 992, 581209, 579888, 579744, 398, 1044, 1732, 1711, 579321, 581884, 581395, 579670, 643, 774, 1021, 83, 1030, 581764, 514, 3049, 582047, 746, 2242, 1641, 580598, 383, 2160, 809, 1002, 1047, 141, 2785, 195, 654, 462, 1284, 581353, 1014, 153, 579886, 1019, 580369, 580357, 580633, 580759, 581729, 1493, 521, 1109, 579328, 1049, 2551, 1018]}, "closers.last year": {"closed": [176, 137, 104, 78, 64, 55, 52, 49, 42, 41, 39, 36, 34, 28, 27, 26, 25, 25, 22, 21, 21, 21, 20, 19, 19, 18, 16, 16, 15, 15, 14, 14, 14, 14, 12, 12, 11, 11, 10, 9, 9, 9, 8, 8, 7, 7, 7, 6, 6, 6, 6, 6, 5, 5, 5, 5, 3, 3, 3, 3, 3, 3, 3, 3, 2, 2, 2, 2, 2, 2, 2, 2, 2, 2, 2, 2, 2, 2, 2, 2, 1, 1, 1, 1, 1, 1, 1, 1, 1, 1, 1, 1, 1], "closers": ["Dmitry Borodaenko", "Vladimir Kuklin", "Bogdan Dobrelya", "Sergey Lukjanov", "Dmitry Pyzhov", "Mike Scherbakov", "Matthew Mosesohn", "dburmistrov", "Serg Melikyan", "tatyana.leontovich@gmail.com", "efedorova", "Roman Podolyaka", "Timur Sufiev", "enikanorov", "Valeriy Ponomaryov", "idv1985", "alekseyk.ru@gmail.com", "vkramskikh@gmail.com", "igor@kalnitsky.org", "Aleksandra Fedorova", "holser@gmail.com", "jkirnosova", "mrasskazov", "dmitryme", "Ilya Sviridov", "vsharshov@mirantis.com", "Dina Belova", "Ruslan Kamaldinov", "Evgeniy L", "xenolog", "Dmitry Shulyak", "e0ne", "ishishkin", "vparakhin", "gcon.monolake@gmail.com", "Oleg Bondarev", "Alexander Ignatov", "Victor Sergeyev", "Angus Salkeld", "Illia Khudoshyn", "Konovalov-Nik", "sbogatkin", "iyozhikov", "nmarkov", "Boris Pavlovic", "Denis Egorenko", "Sergey Galkin", "Denis M", "diakunchikov", "ipovolotskaya", "prmtl", "xdeller", "Pekelny Ilya", "Sergey Kolekonov", "Sergey Reshetnyak", "Yuriy Taraday", "Andrew Lazarev", "dtyzhnenko", "Ilya Shakhat", "nerminamiller", "pkaminski", "Ryan Moe", "Stan Lagun", "Vladimir Kozhukalov", "akislitsky", "Alexei Kornienko", "Andrew Woodward", "Andrey Epifanov", "Andrey Kurilin", "Andrey Pavlov", "Ann Kamyshnikova", "Dmitriy Ukhlov", "Elena Ezhova", "jaypipes", "Piotr Siwczak", "Sergey Nikitin", "srogov", "Vadim Rovachev", "Yuriy Zveryanskyy", "yyekovenko", "Alexander Kuznetsov", "DreidelLhasa@yahoo.com", "dsokolov@mirantis.com", "ekozhemyakin", "eshumakher", "fsoppelsa", "Pavlo Shchelokovskyy", "Roman Prykhodchenko", "Sergey Kraynev", "vitalij-ua", "Vitaly Gridnev", "Vladyslav Drok", "Yaroslav Lobankov"], "id": [271, 2250, 1426, 731, 1639, 1837, 1637, 579937, 1613, 578473, 1635, 140, 1070, 505, 1266, 579717, 579690, 579711, 580278, 1681, 580709, 578030, 580104, 1012, 1664, 579741, 1029, 993, 3114, 579688, 283, 242, 579691, 580548, 579689, 509, 772, 363, 954, 2784, 992, 581209, 579888, 579744, 398, 1044, 1732, 1711, 579321, 581884, 581395, 579670, 643, 774, 1021, 83, 1030, 581764, 514, 3049, 582047, 746, 2242, 1641, 580598, 383, 2160, 809, 1002, 1047, 141, 2785, 195, 654, 462, 1284, 581353, 1014, 153, 579886, 1019, 580369, 580357, 580633, 580759, 581729, 1493, 521, 1109, 579328, 1049, 2551, 1018]}}