{"authors.": {"authors": ["Armando Migliaccio", "Dan Wendlandt", "Brad Hall", "Somik Behera", "Salvatore Orlando", "arosen", "Dave Lapsley", "Peter Balland", "Jacob Cherkas", "tkraus"], "commits": [903, 440, 280, 73, 21, 18, 16, 3, 1, 1], "id": [477, 422, 420, 418, 419, 468, 451, 1640, 2046, 900]}, "authors.last month": {"authors": ["Armando Migliaccio", "Dan Wendlandt", "Brad Hall", "Somik Behera", "Salvatore Orlando", "arosen", "Dave Lapsley", "Peter Balland", "Jacob Cherkas", "tkraus"], "commits": [903, 440, 280, 73, 21, 18, 16, 3, 1, 1], "id": [477, 422, 420, 418, 419, 468, 451, 1640, 2046, 900]}, "authors.last year": {"authors": ["Armando Migliaccio", "Dan Wendlandt", "Brad Hall", "Somik Behera", "Salvatore Orlando", "arosen", "Dave Lapsley", "Peter Balland", "Jacob Cherkas", "tkraus"], "commits": [903, 440, 280, 73, 21, 18, 16, 3, 1, 1], "id": [477, 422, 420, 418, 419, 468, 451, 1640, 2046, 900]}}