{"authors.": {"authors": ["SpamapS", "Tim Miller", "Lucas Alvares Gomes", "Monty Taylor", "Ben Nemec", "Christian Berendt", "James E. Blair", "James Slagle", "Jeremy Stanley", "JUN JIE NAN", "Motohiro OTSUKA", "Sascha Peilicke", "Steve Kowalik"], "commits": [8, 5, 3, 2, 1, 1, 1, 1, 1, 1, 1, 1, 1], "id": [597, 547, 85, 1, 193, 361, 15, 926, 294, 687, 819, 81, 830]}, "authors.last month": {"authors": [], "commits": [], "id": []}, "authors.last year": {"authors": ["SpamapS", "Ben Nemec", "Christian Berendt", "Motohiro OTSUKA", "Steve Kowalik"], "commits": [2, 1, 1, 1, 1], "id": [597, 193, 361, 819, 830]}}